pydeepflow/__init__.py
pydeepflow/activations.py
pydeepflow/batch_normalization.py
pydeepflow/checkpoints.py
pydeepflow/cross_validator.py
pydeepflow/device.py
pydeepflow/early_stopping.py
pydeepflow/learning_rate_scheduler.py
pydeepflow/losses.py
pydeepflow/main.py
pydeepflow/model.py
pydeepflow/regularization.py
pydeepflow-1.0.0.dist-info/LICENSE
pydeepflow-1.0.0.dist-info/METADATA
pydeepflow-1.0.0.dist-info/WHEEL
pydeepflow-1.0.0.dist-info/entry_points.txt
pydeepflow-1.0.0.dist-info/top_level.txt
pydeepflow-1.0.0.dist-info/RECORD
