Metadata-Version: 2.1
Name: pydeepflow
Version: 1.0.0
Summary: A deep learning package optimized for performing Deep Learning Tasks, easy to learn and integrate into projects
Home-page: https://github.com/ravin-d-27/PyDeepFlow
Author: Ravin D
Author-email: ravin.d3107@outlook.com
License: MIT
Project-URL: Bug Tracker, https://github.com/ravin-d-27/PyDeepFlow/issues
Project-URL: Source Code, https://github.com/ravin-d-27/PyDeepFlow
Project-URL: Documentation, https://github.com/ravin-d-27/PyDeepFlow/wiki
Keywords: deep-learning artificial-intelligence neural-networks tensorflow pytorch
Classifier: Programming Language :: Python :: 3
Classifier: License :: OSI Approved :: MIT License
Classifier: Operating System :: OS Independent
Classifier: Topic :: Scientific/Engineering :: Artificial Intelligence
Requires-Python: >=3.6
License-File: LICENSE
Requires-Dist: numpy >=1.23.5
Requires-Dist: pandas >=1.5.3
Requires-Dist: scikit-learn >=1.2.0
Requires-Dist: jupyter >=1.0.0
Requires-Dist: tqdm >=4.64.1
Requires-Dist: colorama >=0.4.6
Requires-Dist: matplotlib
Provides-Extra: gpu
Requires-Dist: cupy >=9.6.0 ; extra == 'gpu'
Provides-Extra: testing
Requires-Dist: pytest >=6.2.5 ; extra == 'testing'
